b3get/__init__.py
b3get/__main__.py
b3get/api.py
b3get/cli.py
b3get/datasets.py
b3get/utils.py
b3get-0.4.1.dist-info/AUTHORS.rst
b3get-0.4.1.dist-info/LICENSE
b3get-0.4.1.dist-info/METADATA
b3get-0.4.1.dist-info/WHEEL
b3get-0.4.1.dist-info/entry_points.txt
b3get-0.4.1.dist-info/top_level.txt
b3get-0.4.1.dist-info/RECORD
